rplint/__init__.py
rplint/__main__.py
rplint/main.py
rplint/main.py.orig
rplint-0.7.1.dist-info/entry_points.txt
rplint-0.7.1.dist-info/LICENSE
rplint-0.7.1.dist-info/WHEEL
rplint-0.7.1.dist-info/METADATA
rplint-0.7.1.dist-info/RECORD
