Metadata-Version: 2.1
Name: rplint
Version: 0.7.1
Summary: 
Author: Jim Anderson
Author-email: jima.coding@gmail.com
Requires-Python: >=3.7,<4.0
Classifier: Programming Language :: Python :: 3
Classifier: Programming Language :: Python :: 3.7
Classifier: Programming Language :: Python :: 3.8
Classifier: Programming Language :: Python :: 3.9
Requires-Dist: click (>=7.1.2,<8.0.0)
